wbcrm/__init__.py
wbcrm/apps.py
wbcrm/dynamic_preferences_registry.py
wbcrm/preferences.py
wbcrm/tasks.py
wbcrm/typings.py
wbcrm/urls.py
wbcrm/admin/__init__.py
wbcrm/admin/accounts.py
wbcrm/admin/activities.py
wbcrm/admin/groups.py
wbcrm/admin/products.py
wbcrm/configurations/__init__.py
wbcrm/configurations/base.py
wbcrm/factories/__init__.py
wbcrm/factories/accounts.py
wbcrm/factories/activities.py
wbcrm/factories/groups.py
wbcrm/factories/products.py
wbcrm/filters/__init__.py
wbcrm/filters/accounts.py
wbcrm/filters/activities.py
wbcrm/filters/groups.py
wbcrm/filters/products.py
wbcrm/filters/signals.py
wbcrm/fixtures/wbcrm.json
wbcrm/kpi_handlers/activities.py
wbcrm/locale/de/LC_MESSAGES/django.po
wbcrm/migrations/0001_initial_squashed_squashed_0032_productcompanyrelationship_alter_product_prospects_and_more.py
wbcrm/migrations/0002_alter_activity_repeat_choice.py
wbcrm/migrations/0003_remove_activity_external_id_and_more.py
wbcrm/migrations/0004_alter_activity_status.py
wbcrm/migrations/0005_account_accountrole_accountroletype_and_more.py
wbcrm/migrations/0006_alter_activity_location.py
wbcrm/migrations/0007_alter_account_status.py
wbcrm/migrations/0008_alter_activity_options.py
wbcrm/migrations/0009_alter_account_is_public.py
wbcrm/migrations/0010_alter_account_reference_id.py
wbcrm/migrations/0011_activity_summary.py
wbcrm/migrations/0012_alter_activity_summary.py
wbcrm/migrations/0013_account_action_plan_account_relationship_status_and_more.py
wbcrm/migrations/0014_alter_account_relationship_status.py
wbcrm/migrations/0015_alter_activity_type.py
wbcrm/migrations/0016_auto_20241205_1015.py
wbcrm/migrations/__init__.py
wbcrm/models/__init__.py
wbcrm/models/accounts.py
wbcrm/models/activities.py
wbcrm/models/groups.py
wbcrm/models/products.py
wbcrm/models/recurrence.py
wbcrm/models/llm/activity_summaries.py
wbcrm/models/llm/analyze_relationship.py
wbcrm/report/activity_report.py
wbcrm/serializers/__init__.py
wbcrm/serializers/accounts.py
wbcrm-2.2.6.dist-info/METADATA
wbcrm-2.2.6.dist-info/WHEEL
wbcrm-2.2.6.dist-info/RECORD
