Metadata-Version: 2.4
Name: wbcrm
Version: 2.2.6
Summary: A workbench module that contains all the functionality related to a customer relationship management.
Author-email: Christopher Wittlinger <c.wittlinger@stainly.com>
Requires-Dist: django-eventtools==1.*
Requires-Dist: google-api-python-client==2.62.*
Requires-Dist: google-auth-httplib2==0.1.*
Requires-Dist: google-auth-oauthlib==0.5.*
Requires-Dist: wbcore
Requires-Dist: xlsxwriter==3.*
